{
  "subjects": [
    {
      "sno": "1",
      "subject": "Compiler Design",
      "held": 35,
      "present": 29,
      "percentage": "82.9%"
    },
    {
      "sno": "2",
      "subject": "Cloud Computing",
      "held": 15,
      "present": 12,
      "percentage": "80.0%"
    },
    {
      "sno": "3",
      "subject": "Cryptography & Network Security",
      "held": 36,
      "present": 31,
      "percentage": "86.1%"
    },
    {
      "sno": "4",
      "subject": "Machine Learning",
      "held": 28,
      "present": 24,
      "percentage": "85.7%"
    },
    {
      "sno": "5",
      "subject": "Software Project Management",
      "held": 28,
      "present": 22,
      "percentage": "78.6%"
    },
    {
      "sno": "6",
      "subject": "Disaster Management",
      "held": 34,
      "present": 33,
      "percentage": "97.1%"
    },
    {
      "sno": "7",
      "subject": "Cloud Computing Lab",
      "held": 15,
      "present": 15,
      "percentage": "100.0%"
    },
    {
      "sno": "8",
      "subject": "Cryptography & Network Security Lab",
      "held": 27,
      "present": 21,
      "percentage": "77.8%"
    },
    {
      "sno": "9",
      "subject": "Soft Skills",
      "held": 21,
      "present": 21,
      "percentage": "100.0%"
    },
    {
      "sno": "10",
      "subject": "Technical Paper Writing & IPR",
      "held": 17,
      "present": 15,
      "percentage": "88.2%"
    },
    {
      "sno": "11",
      "subject": "ASSOCIATION",
      "held": 9,
      "present": 8,
      "percentage": "88.9%"
    },
    {
      "sno": "12",
      "subject": "Technical Training",
      "held": 24,
      "present": 21,
      "percentage": "87.5%"
    }
  ],
  "overall_percentage": "87.2 %",
  "timestamp": "21/02/2026 03:34"
}